langterm/__init__.py
langterm-0.0.1.dist-info/METADATA
langterm-0.0.1.dist-info/WHEEL
langterm-0.0.1.dist-info/top_level.txt
langterm-0.0.1.dist-info/RECORD
